{"is_source_file": true, "format": "jsx", "description": ".jsx file: RecipeGrid.jsx", "external_files": [], "external_methods": [], "published": [], "classes": [], "methods": [], "calls": [], "search-terms": ["RecipeGrid.jsx", "jsx"], "state": 2, "file_id": 16, "knowledge_revision": 53, "git_revision": "21b10f1ea81542bdd6fe0e8d517b41f6790adcd1", "revision_history": [{"34": ""}, {"53": "21b10f1ea81542bdd6fe0e8d517b41f6790adcd1"}], "ctags": [], "filename": "food_recipe_frontend/src/components/RecipeGrid.jsx", "format-version": 4, "code-base-name": "https://github.com/kavia-common/recipe-explorer-29795-29807.git:kavia-main"}